agora_mcp/__init__.py
agora_mcp/server.py
agora_mcp-0.1.10.dist-info/METADATA
agora_mcp-0.1.10.dist-info/WHEEL
agora_mcp-0.1.10.dist-info/entry_points.txt
agora_mcp-0.1.10.dist-info/RECORD
