Metadata-Version: 2.4
Name: agora-mcp
Version: 0.1.10
Summary: Agora MCP server to search & buy across thousands of online stores
Author-email: Pol Alvarez <pol@fewsats.com>, Jordi Montes <jordi@fewsats.com>
Requires-Python: >=3.10
Requires-Dist: agora-python>=0.0.8
Requires-Dist: mcp>=1.6.0
